LICENSE
README.md
setup.py
routeros_ssh_connector/__init__.py
routeros_ssh_connector/connector.py
routeros_ssh_connector.egg-info/PKG-INFO
routeros_ssh_connector.egg-info/SOURCES.txt
routeros_ssh_connector.egg-info/dependency_links.txt
routeros_ssh_connector.egg-info/requires.txt
routeros_ssh_connector.egg-info/top_level.txt