Metadata-Version: 2.1
Name: routeros-ssh-connector
Version: 1.7.1
Summary: A python-based SSH API for MikroTik devices
Home-page: https://github.com/d4vidcn/routeros_ssh_connector
Author: d4vidCN
Author-email: d4vidcn.code@gmail.com
License: MIT
Project-URL: Bug Tracker, https://github.com/d4vidcn/routeros_ssh_connector/issues
Keywords: mikrotik,routeros,ssh,connector,ssh connector,mikrotik routeros,mikrotik ssh,routeros ssh
Platform: UNKNOWN
Classifier: Programming Language :: Python :: 3
Classifier: License :: OSI Approved :: MIT License
Classifier: Operating System :: OS Independent
